{"type":"cycle-start", "list_name":"default", "id":0, "hostname":"LAPTOP", "start_time":1733575543}
{"type":"tracelb", "version":"0.1", "userid":0, "method":"udp-dport", "src":"192.168.1.27", "dst":"130.104.228.159", "sport":62062, "dport":33435, "start":{"sec":1733575543, "usec":871298, "ftime":"2024-12-07 09:45:43"}, "probe_size":44, "firsthop":1, "attempts":2, "confidence":95, "tos":0, "gaplimit":3, "wait_timeout":5, "wait_probe":25, "probec":50, "probec_max":50, "nodec":2, "linkc":2, "nodes":[{"addr":"192.168.1.1", "q_ttl":1, "linkc":1, "links":[[{"addr":"191.112.0.1", "probes":[{"tx":{"sec":1733575544, "usec":121475}, "replyc":1, "ttl":2, "attempt":0, "flowid":33435, "replies":[{"rx":{"sec":1733575544, "usec":125988}, "ttl":254, "rtt":4.513, "ipid":673, "icmp_type":11, "icmp_code":0, "icmp_q_tos":0, "icmp_q_ttl":1}]},{"tx":{"sec":1733575544, "usec":372448}, "replyc":1, "ttl":2, "attempt":0, "flowid":33436, "replies":[{"rx":{"sec":1733575544, "usec":376972}, "ttl":254, "rtt":4.524, "ipid":674, "icmp_type":11, "icmp_code":0, "icmp_q_tos":0, "icmp_q_ttl":1}]},{"tx":{"sec":1733575544, "usec":623493}, "replyc":1, "ttl":2, "attempt":0, "flowid":33437, "replies":[{"rx":{"sec":1733575544, "usec":631757}, "ttl":254, "rtt":8.264, "ipid":694, "icmp_type":11, "icmp_code":0, "icmp_q_tos":0, "icmp_q_ttl":1}]},{"tx":{"sec":1733575544, "usec":874142}, "replyc":1, "ttl":2, "attempt":0, "flowid":33438, "replies":[{"rx":{"sec":1733575544, "usec":879138}, "ttl":254, "rtt":4.996, "ipid":695, "icmp_type":11, "icmp_code":0, "icmp_q_tos":0, "icmp_q_ttl":1}]},{"tx":{"sec":1733575545, "usec":124499}, "replyc":1, "ttl":2, "attempt":0, "flowid":33439, "replies":[{"rx":{"sec":1733575545, "usec":135996}, "ttl":254, "rtt":11.497, "ipid":696, "icmp_type":11, "icmp_code":0, "icmp_q_tos":0, "icmp_q_ttl":1}]},{"tx":{"sec":1733575545, "usec":375415}, "replyc":1, "ttl":2, "attempt":0, "flowid":33440, "replies":[{"rx":{"sec":1733575545, "usec":380471}, "ttl":254, "rtt":5.056, "ipid":697, "icmp_type":11, "icmp_code":0, "icmp_q_tos":0, "icmp_q_ttl":1}]}]}]]},{"addr":"191.112.0.1", "q_ttl":1, "linkc":1, "links":[[{"addr":"10.50.3.9", "probes":[{"tx":{"sec":1733575545, "usec":625886}, "replyc":1, "ttl":3, "attempt":0, "flowid":33435, "replies":[{"rx":{"sec":1733575545, "usec":629589}, "ttl":253, "rtt":3.703, "ipid":99, "icmp_type":11, "icmp_code":0, "icmp_q_tos":0, "icmp_q_ttl":1}]},{"tx":{"sec":1733575551, "usec":381650}, "replyc":1, "ttl":3, "attempt":0, "flowid":33438, "replies":[{"rx":{"sec":1733575551, "usec":385854}, "ttl":253, "rtt":4.204, "ipid":635, "icmp_type":11, "icmp_code":0, "icmp_q_tos":0, "icmp_q_ttl":1}]},{"tx":{"sec":1733575557, "usec":389196}, "replyc":1, "ttl":3, "attempt":0, "flowid":33442, "replies":[{"rx":{"sec":1733575557, "usec":393148}, "ttl":253, "rtt":3.952, "ipid":64, "icmp_type":11, "icmp_code":0, "icmp_q_tos":0, "icmp_q_ttl":1}]},{"tx":{"sec":1733575557, "usec":639613}, "replyc":1, "ttl":3, "attempt":0, "flowid":33443, "replies":[{"rx":{"sec":1733575557, "usec":643764}, "ttl":253, "rtt":4.151, "ipid":644, "icmp_type":11, "icmp_code":0, "icmp_q_tos":0, "icmp_q_ttl":1}]},{"tx":{"sec":1733575557, "usec":890207}, "replyc":1, "ttl":3, "attempt":0, "flowid":33444, "replies":[{"rx":{"sec":1733575557, "usec":894592}, "ttl":253, "rtt":4.385, "ipid":349, "icmp_type":11, "icmp_code":0, "icmp_q_tos":0, "icmp_q_ttl":1}]},{"tx":{"sec":1733575558, "usec":140994}, "replyc":1, "ttl":3, "attempt":0, "flowid":33445, "replies":[{"rx":{"sec":1733575558, "usec":145101}, "ttl":253, "rtt":4.107, "ipid":233, "icmp_type":11, "icmp_code":0, "icmp_q_tos":0, "icmp_q_ttl":1}]},{"tx":{"sec":1733575558, "usec":391527}, "replyc":1, "ttl":3, "attempt":0, "flowid":33435, "replies":[{"rx":{"sec":1733575558, "usec":395274}, "ttl":253, "rtt":3.747, "ipid":797, "icmp_type":11, "icmp_code":0, "icmp_q_tos":0, "icmp_q_ttl":1}]},{"tx":{"sec":1733575558, "usec":641634}, "replyc":1, "ttl":3, "attempt":0, "flowid":33435, "replies":[{"rx":{"sec":1733575558, "usec":644792}, "ttl":253, "rtt":3.158, "ipid":851, "icmp_type":11, "icmp_code":0, "icmp_q_tos":0, "icmp_q_ttl":1}]},{"tx":{"sec":1733575558, "usec":892252}, "replyc":1, "ttl":3, "attempt":0, "flowid":33435, "replies":[{"rx":{"sec":1733575558, "usec":895955}, "ttl":253, "rtt":3.703, "ipid":896, "icmp_type":11, "icmp_code":0, "icmp_q_tos":0, "icmp_q_ttl":1}]},{"tx":{"sec":1733575559, "usec":142324}, "replyc":1, "ttl":3, "attempt":0, "flowid":33435, "replies":[{"rx":{"sec":1733575559, "usec":145754}, "ttl":253, "rtt":3.430, "ipid":948, "icmp_type":11, "icmp_code":0, "icmp_q_tos":0, "icmp_q_ttl":1}]}]}, {"addr":"10.50.3.21", "probes":[{"tx":{"sec":1733575550, "usec":880156}, "replyc":1, "ttl":3, "attempt":1, "flowid":33436, "replies":[{"rx":{"sec":1733575550, "usec":897259}, "ttl":253, "rtt":17.103, "ipid":251, "icmp_type":11, "icmp_code":0, "icmp_q_tos":0, "icmp_q_ttl":1}]},{"tx":{"sec":1733575551, "usec":130693}, "replyc":1, "ttl":3, "attempt":0, "flowid":33437, "replies":[{"rx":{"sec":1733575551, "usec":135208}, "ttl":253, "rtt":4.515, "ipid":782, "icmp_type":11, "icmp_code":0, "icmp_q_tos":0, "icmp_q_ttl":1}]},{"tx":{"sec":1733575556, "usec":636405}, "replyc":1, "ttl":3, "attempt":1, "flowid":33439, "replies":[{"rx":{"sec":1733575556, "usec":640852}, "ttl":253, "rtt":4.447, "ipid":923, "icmp_type":11, "icmp_code":0, "icmp_q_tos":0, "icmp_q_ttl":1}]},{"tx":{"sec":1733575556, "usec":887290}, "replyc":1, "ttl":3, "attempt":0, "flowid":33440, "replies":[{"rx":{"sec":1733575556, "usec":890702}, "ttl":253, "rtt":3.412, "ipid":112, "icmp_type":11, "icmp_code":0, "icmp_q_tos":0, "icmp_q_ttl":1}]},{"tx":{"sec":1733575557, "usec":138137}, "replyc":1, "ttl":3, "attempt":0, "flowid":33441, "replies":[{"rx":{"sec":1733575557, "usec":141751}, "ttl":253, "rtt":3.614, "ipid":8, "icmp_type":11, "icmp_code":0, "icmp_q_tos":0, "icmp_q_ttl":1}]},{"tx":{"sec":1733575559, "usec":393240}, "replyc":1, "ttl":3, "attempt":0, "flowid":33435, "replies":[{"rx":{"sec":1733575559, "usec":396851}, "ttl":253, "rtt":3.611, "ipid":1001, "icmp_type":11, "icmp_code":0, "icmp_q_tos":0, "icmp_q_ttl":1}]}]}],[{"addr":"*"}]]}]}
{"type":"cycle-stop", "list_name":"default", "id":0, "hostname":"LAPTOP", "stop_time":1733575622}
